MasteringGoZhongwenbanFix1/README.md
MasteringGoZhongwenbanFix1/__init__.py
MasteringGoZhongwenbanFix1/__main__.py
MasteringGoZhongwenbanFix1/file.epub
MasteringGoZhongwenbanFix1/index.html
MasteringGoZhongwenbanFix1/css/__init__.py
MasteringGoZhongwenbanFix1/css/annotations.css
MasteringGoZhongwenbanFix1/css/main.css
MasteringGoZhongwenbanFix1/css/normalize.css
MasteringGoZhongwenbanFix1/css/popup.css
MasteringGoZhongwenbanFix1/font/__init__.py
MasteringGoZhongwenbanFix1/font/fontello.eot
MasteringGoZhongwenbanFix1/font/fontello.svg
MasteringGoZhongwenbanFix1/font/fontello.ttf
MasteringGoZhongwenbanFix1/font/fontello.woff
MasteringGoZhongwenbanFix1/img/__init__.py
MasteringGoZhongwenbanFix1/img/annotator-glyph-sprite.png
MasteringGoZhongwenbanFix1/img/annotator-icon-sprite.png
MasteringGoZhongwenbanFix1/img/apple-touch-icon.png
MasteringGoZhongwenbanFix1/img/cancelfullscreen.png
MasteringGoZhongwenbanFix1/img/close.png
MasteringGoZhongwenbanFix1/img/fullscreen.png
MasteringGoZhongwenbanFix1/img/loader.gif
MasteringGoZhongwenbanFix1/img/menu-icon.png
MasteringGoZhongwenbanFix1/img/save.png
MasteringGoZhongwenbanFix1/img/saved.png
MasteringGoZhongwenbanFix1/img/settings-s.png
MasteringGoZhongwenbanFix1/img/settings.png
MasteringGoZhongwenbanFix1/img/star.png
MasteringGoZhongwenbanFix1/js/__init__.py
MasteringGoZhongwenbanFix1/js/epub.js
MasteringGoZhongwenbanFix1/js/epub.min.js
MasteringGoZhongwenbanFix1/js/epub.min.map
MasteringGoZhongwenbanFix1/js/hooks.min.js
MasteringGoZhongwenbanFix1/js/hooks.min.map
MasteringGoZhongwenbanFix1/js/reader.js
MasteringGoZhongwenbanFix1/js/reader.js.map
MasteringGoZhongwenbanFix1/js/reader.min.js
MasteringGoZhongwenbanFix1/js/reader.min.map
MasteringGoZhongwenbanFix1/js/hooks/__init__.py
MasteringGoZhongwenbanFix1/js/hooks/extensions/__init__.py
MasteringGoZhongwenbanFix1/js/hooks/extensions/highlight.js
MasteringGoZhongwenbanFix1/js/libs/__init__.py
MasteringGoZhongwenbanFix1/js/libs/jquery.min.js
mastering_go_zhongwenban_fix1-2025.3.25.1.dist-info/METADATA
mastering_go_zhongwenban_fix1-2025.3.25.1.dist-info/WHEEL
mastering_go_zhongwenban_fix1-2025.3.25.1.dist-info/entry_points.txt
mastering_go_zhongwenban_fix1-2025.3.25.1.dist-info/top_level.txt
mastering_go_zhongwenban_fix1-2025.3.25.1.dist-info/RECORD
